{
  "machine": {
    "id": "i-03e60461ce6f516c7",
    "name": "i-03e60461ce6f516c7",
    "type": "c4.4xlarge",
    "imageId": "ami-0846d99d2e855025b",
    "cloud": "ec2",
    "zone": "us-east-1e",
    "region": "us-east-1",
    "spawned": "2019-05-01T13:11:48Z"
  },
  "worker": {
    "id": "i-03e60461ce6f516c7",
    "provisioner": "aws-provisioner-v1",
    "type": "gecko-1-b-win2012",
    "group": "us-east-1",
    "implementation": "generic-worker",
    "expires": "0001-01-01T00:00:00Z",
    "firstClaim": "2019-05-01T13:18:29.06Z",
    "tasks": [
      {
        "id": "KjZpl10AScOwU_6kywnU0A",
        "run": 0
      },
      {
        "id": "XxuIyOr-TS6tl4JkxxD0eQ",
        "run": 0
      },
      {
        "id": "Sklxrl0USDWqC0odiyqf_g",
        "run": 0
      },
      {
        "id": "EZv3ShV7SUan1RclrpPMQw",
        "run": 0
      },
      {
        "id": "ar8dsX6uT-6N2HHEJcKBKQ",
        "run": 0
      },
      {
        "id": "JAvvBRaTR6CRTJCUab4IMQ",
        "run": 0
      }
    ]
  },
  "state": "working"
}