{
  "machine": {
    "id": "i-092531a36fd093880",
    "name": "i-092531a36fd093880",
    "type": "c4.4xlarge",
    "imageId": "ami-07c14941bbdf1e451",
    "cloud": "ec2",
    "zone": "eu-central-1c",
    "region": "eu-central-1",
    "spawned": "2019-05-02T03:14:48Z"
  },
  "worker": {
    "id": "i-092531a36fd093880",
    "provisioner": "aws-provisioner-v1",
    "type": "gecko-1-b-win2012",
    "group": "eu-central-1",
    "implementation": "generic-worker",
    "expires": "0001-01-01T00:00:00Z",
    "firstClaim": "2019-05-02T03:21:39.549Z",
    "tasks": null
  },
  "state": "waiting"
}