{
  "machine": {
    "id": "i-014c6c7e2183e5dc2",
    "name": "i-014c6c7e2183e5dc2",
    "type": "c5d.4xlarge",
    "imageId": "ami-0dedc5db10ec003af",
    "cloud": "ec2",
    "zone": "us-east-1c",
    "region": "us-east-1",
    "spawned": "2019-05-13T17:29:12Z"
  },
  "worker": {
    "id": "i-014c6c7e2183e5dc2",
    "provisioner": "aws-provisioner-v1",
    "type": "gecko-1-b-linux",
    "group": "us-east-1",
    "implementation": "docker-worker",
    "expires": "0001-01-01T00:00:00Z",
    "firstClaim": "2019-05-13T17:29:52.155Z",
    "tasks": [
      {
        "id": "ecWM0-fNSxOjZKPC7KMAHA",
        "run": 0
      },
      {
        "id": "Q8czYTIoTCW4A__PocfFSg",
        "run": 0
      },
      {
        "id": "TJxVbFZuTr-uy-IxJeaqBQ",
        "run": 0
      },
      {
        "id": "NFy_5hamQOGGCkd488JpnQ",
        "run": 0
      },
      {
        "id": "ENBNGvJkSBq-Cd1RB0q1Zw",
        "run": 0
      }
    ]
  },
  "state": "working"
}