{
  "machine": {
    "id": "i-029cf31509bb4e5b5",
    "name": "i-029cf31509bb4e5b5",
    "type": "c5d.4xlarge",
    "imageId": "ami-06adcae0cf519fda6",
    "cloud": "ec2",
    "zone": "us-west-1b",
    "region": "us-west-1",
    "spawned": "2019-05-07T08:48:12Z"
  },
  "worker": {
    "id": "i-029cf31509bb4e5b5",
    "provisioner": "aws-provisioner-v1",
    "type": "gecko-1-b-linux",
    "group": "us-west-1",
    "implementation": "docker-worker",
    "expires": "0001-01-01T00:00:00Z",
    "firstClaim": "2019-05-07T08:48:50.708Z",
    "tasks": [
      {
        "id": "G2xqtYyNTt6SeBIGLetHHQ",
        "run": 0
      },
      {
        "id": "AQII62D2Qza3XnI5X74qMQ",
        "run": 0
      }
    ]
  },
  "state": "working"
}