{
  "machine": {
    "id": "i-055f95c96aa3f3add",
    "name": "i-055f95c96aa3f3add",
    "type": "c5d.4xlarge",
    "imageId": "ami-06adcae0cf519fda6",
    "cloud": "ec2",
    "zone": "us-west-1b",
    "region": "us-west-1",
    "spawned": "2019-05-14T04:24:28Z"
  },
  "worker": {
    "id": "i-055f95c96aa3f3add",
    "provisioner": "aws-provisioner-v1",
    "type": "gecko-1-b-linux",
    "group": "us-west-1",
    "implementation": "docker-worker",
    "expires": "0001-01-01T00:00:00Z",
    "firstClaim": "2019-05-14T04:25:07.264Z",
    "tasks": [
      {
        "id": "eAM3HlMjReGAJAIaEliGew",
        "run": 0
      },
      {
        "id": "PuzodQRHRdSYZa3zJ-BpBg",
        "run": 0
      },
      {
        "id": "EApZOKuTRoelfNODu632aA",
        "run": 0
      }
    ]
  },
  "state": "working"
}