{
  "machine": {
    "id": "i-006888d1b38be756f",
    "name": "i-006888d1b38be756f",
    "type": "c4.4xlarge",
    "imageId": "ami-07e19b86df6b78c84",
    "cloud": "ec2",
    "zone": "us-west-2c",
    "region": "us-west-2",
    "spawned": "2019-05-02T12:20:04Z"
  },
  "worker": {
    "id": "i-006888d1b38be756f",
    "provisioner": "aws-provisioner-v1",
    "type": "gecko-2-b-win2012",
    "group": "us-west-2",
    "implementation": "generic-worker",
    "expires": "0001-01-01T00:00:00Z",
    "firstClaim": "2019-05-02T12:27:22.096Z",
    "tasks": [
      {
        "id": "dIrCjet3TBKzd70K08hbtw",
        "run": 0
      },
      {
        "id": "QtNjeKETS5erwRf_Vrhwcg",
        "run": 0
      },
      {
        "id": "RH0P_6ncQMapbLvSX_DUyA",
        "run": 0
      },
      {
        "id": "cxddSu2HSe-xpGaOHYTeeQ",
        "run": 0
      },
      {
        "id": "XjTROMuLR1qMcQ3i-dkCJQ",
        "run": 0
      }
    ]
  },
  "state": "working"
}