{
  "machine": {
    "id": "i-00b80bc072ecf1a21",
    "name": "i-00b80bc072ecf1a21",
    "type": "c5.2xlarge",
    "imageId": "ami-0e8b2d5e665e5c0d8",
    "cloud": "ec2",
    "zone": "us-west-1c",
    "region": "us-west-1",
    "spawned": "2019-05-14T10:52:24Z"
  },
  "worker": {
    "id": "i-00b80bc072ecf1a21",
    "provisioner": "aws-provisioner-v1",
    "type": "gecko-t-win10-64",
    "group": "us-west-1",
    "implementation": "generic-worker",
    "expires": "0001-01-01T00:00:00Z",
    "firstClaim": "2019-05-14T11:00:18.695Z",
    "tasks": null
  },
  "state": "waiting"
}