{
  "machine": {
    "id": "i-086546d4dfd98bc68",
    "name": "i-086546d4dfd98bc68",
    "type": "c5.2xlarge",
    "imageId": "ami-0f92f97538820c73f",
    "cloud": "ec2",
    "zone": "eu-central-1b",
    "region": "eu-central-1",
    "spawned": "2019-05-13T09:31:30Z"
  },
  "worker": {
    "id": "i-086546d4dfd98bc68",
    "provisioner": "aws-provisioner-v1",
    "type": "gecko-t-win10-64",
    "group": "eu-central-1",
    "implementation": "generic-worker",
    "expires": "0001-01-01T00:00:00Z",
    "firstClaim": "2019-05-13T09:38:53.382Z",
    "tasks": [
      {
        "id": "WPdJNoT5Qxi6yLfNvpBAfA",
        "run": 0
      },
      {
        "id": "exVszrsKRrSk_x0AiXKaog",
        "run": 0
      },
      {
        "id": "GnB7wG0tTTGx3kTgWRYMcA",
        "run": 0
      },
      {
        "id": "BipRBgT_TaKHdoKdig3mhQ",
        "run": 0
      },
      {
        "id": "DGTwW99yTo-uDxpiqNUaDw",
        "run": 0
      },
      {
        "id": "DXYC3FvMR72lg0199sCE9g",
        "run": 0
      },
      {
        "id": "Y5s-nVy4SOKu7xZ1lMK_nA",
        "run": 0
      },
      {
        "id": "QBPoWB2DSUWX0uKOhEr-RQ",
        "run": 0
      },
      {
        "id": "CQfaWThrR_aYh-Jr_huL7Q",
        "run": 0
      },
      {
        "id": "SLWZ1kWRSWmQiKgUujCGWQ",
        "run": 0
      },
      {
        "id": "T3YbWVO_R2ChDVucLQaAgA",
        "run": 0
      },
      {
        "id": "UKYUPVHnTuuM0bf8st5AHQ",
        "run": 0
      },
      {
        "id": "ZiKLyOX_QgWeC8mGZDAscg",
        "run": 0
      },
      {
        "id": "MzDIBnoDTPWeUECSRR_3dg",
        "run": 0
      },
      {
        "id": "e95REpHwT4OVyM8Ga_KCMg",
        "run": 0
      },
      {
        "id": "Kb4YS0_iQta5mdz2urRr1w",
        "run": 0
      },
      {
        "id": "Nr3HGfG7S6-Lv-W16SQitQ",
        "run": 0
      },
      {
        "id": "WWyofvUPRbWr_7nec7fFoQ",
        "run": 0
      },
      {
        "id": "Lvz2k1pvQVaUiInsWcacLw",
        "run": 0
      },
      {
        "id": "L--WUBa0QMmQhpLjb3UdfQ",
        "run": 0
      }
    ]
  },
  "state": "working"
}