{
  "machine": {
    "id": "i-0b2fec6242e522a1f",
    "name": "i-0b2fec6242e522a1f",
    "type": "c5.2xlarge",
    "imageId": "ami-0d45ea581fe9fba8b",
    "cloud": "ec2",
    "zone": "us-east-1b",
    "region": "us-east-1",
    "spawned": "2019-05-02T11:49:53Z"
  },
  "worker": {
    "id": "i-0b2fec6242e522a1f",
    "provisioner": "aws-provisioner-v1",
    "type": "gecko-t-win10-64",
    "group": "us-east-1",
    "implementation": "generic-worker",
    "expires": "0001-01-01T00:00:00Z",
    "firstClaim": "2019-05-02T11:57:48.71Z",
    "tasks": [
      {
        "id": "Zulad6UGTNScCflnPb3cBw",
        "run": 0
      },
      {
        "id": "aNVQeBk2QJiWhyuTRXjpqQ",
        "run": 0
      },
      {
        "id": "TfYkhDaKTQujKmT3dVulSw",
        "run": 0
      },
      {
        "id": "bvAXnZrRS9y0YSt13ZT9Fw",
        "run": 0
      },
      {
        "id": "UUGmh0vXQ2qpLYmh-5XHQQ",
        "run": 0
      },
      {
        "id": "CLPRledOQTmDZaQtUAxtlQ",
        "run": 0
      },
      {
        "id": "cEaeWj-JQGWJf7lwojwkKA",
        "run": 0
      },
      {
        "id": "G5AjBxs7ThqwJehN6TkHeA",
        "run": 0
      },
      {
        "id": "Hrl8uywPQI6sj5CTSlZucA",
        "run": 0
      },
      {
        "id": "JtLjN5nbQ9myF-iagMaCMA",
        "run": 0
      },
      {
        "id": "J5fQTFlDQaW_bq6u2e4Nug",
        "run": 0
      },
      {
        "id": "SxKrWc-7TtWYADdFBng5MA",
        "run": 0
      },
      {
        "id": "RmNRktwgSyWT84RqDn40CQ",
        "run": 0
      },
      {
        "id": "RbfVGd7zR_egEsy0YGTWOA",
        "run": 0
      },
      {
        "id": "T1kPMr4xQl6S1vvUxvJOeQ",
        "run": 0
      },
      {
        "id": "aWF8aGY6TuyHGSZqbSKFlw",
        "run": 0
      },
      {
        "id": "a7yALWApRyOoMJpag83Y8A",
        "run": 0
      },
      {
        "id": "BC1lE54fSN-bAQGhkjMGoA",
        "run": 0
      },
      {
        "id": "KW4EeBtaRxeLGU-OfiSEFg",
        "run": 0
      },
      {
        "id": "WwFn5C0cSF-pTCdALU1kZw",
        "run": 0
      }
    ]
  },
  "state": "working"
}