{
  "machine": {
    "id": "i-0b6111092da0226ac",
    "name": "i-0b6111092da0226ac",
    "type": "c5.2xlarge",
    "imageId": "ami-028f1c6afbe56913a",
    "cloud": "ec2",
    "zone": "us-west-2a",
    "region": "us-west-2",
    "spawned": "2019-04-30T11:34:33Z"
  },
  "worker": {
    "id": "i-0b6111092da0226ac",
    "provisioner": "aws-provisioner-v1",
    "type": "gecko-t-win10-64",
    "group": "us-west-2",
    "implementation": "generic-worker",
    "expires": "0001-01-01T00:00:00Z",
    "firstClaim": "2019-04-30T11:42:02.683Z",
    "tasks": [
      {
        "id": "BjDC9oKJTvC5Mx65Pj-J5A",
        "run": 0
      },
      {
        "id": "OPPOaEf7TfirBq5ZPhKYEQ",
        "run": 0
      },
      {
        "id": "V1RTVJ8FT0Sx48J8hsyRPQ",
        "run": 0
      },
      {
        "id": "R3Vq9mHETWy9ga-s4bm1DQ",
        "run": 0
      },
      {
        "id": "eNjn5VlkRHy6_0GWVoXAoA",
        "run": 0
      },
      {
        "id": "e7VaR4doT4uMmw-sTu0Wmw",
        "run": 0
      },
      {
        "id": "ZhFlkEbPT5OOuy1QiUiZdg",
        "run": 0
      },
      {
        "id": "X-r1SJuqT_eNMoZPrFOJCg",
        "run": 0
      },
      {
        "id": "Nzs8RN-qRhGFZTJTcBkEkQ",
        "run": 0
      },
      {
        "id": "DsRSZfuaR9SNJZkraYeG9g",
        "run": 0
      },
      {
        "id": "ONw43LEjSdSmZWxg6xVNxw",
        "run": 0
      },
      {
        "id": "dVIwjNDuTQGy2o9X_M21qw",
        "run": 0
      },
      {
        "id": "Xh0ixMWmRv-WOM5f8Op3uw",
        "run": 0
      },
      {
        "id": "GRhPrpCgQpW4ph6Dzq23_g",
        "run": 0
      },
      {
        "id": "DgtTObnaQNKfUh3GAQEQjA",
        "run": 0
      },
      {
        "id": "fdk5MswyQom4QyiSdsdRdQ",
        "run": 0
      },
      {
        "id": "WDIQIFHJQra8n6c1V7vMlg",
        "run": 0
      },
      {
        "id": "CRdx2pjqS6iiMm776tbhjQ",
        "run": 0
      },
      {
        "id": "fMdAlblmQ-KTL7WcMrWTNw",
        "run": 0
      }
    ]
  },
  "state": "working"
}