{
  "machine": {
    "id": "i-0a0c0ce1438b9b297",
    "name": "i-0a0c0ce1438b9b297",
    "type": "c5d.4xlarge",
    "imageId": "ami-051503b3e37cde2f0",
    "cloud": "ec2",
    "zone": "us-east-1b",
    "region": "us-east-1",
    "spawned": "2019-05-13T18:16:25Z"
  },
  "worker": {
    "id": "i-0a0c0ce1438b9b297",
    "provisioner": "aws-provisioner-v1",
    "type": "gecko-3-b-linux",
    "group": "us-east-1",
    "implementation": "docker-worker",
    "expires": "0001-01-01T00:00:00Z",
    "firstClaim": "2019-05-13T18:17:14.44Z",
    "tasks": [
      {
        "id": "HASY5fAqQ-yHKtSZGcSxVg",
        "run": 0
      },
      {
        "id": "NAldV0hNRJi87IVmcutwJg",
        "run": 0
      },
      {
        "id": "A_rRNpi-SBu4g0ul71Ovlg",
        "run": 0
      },
      {
        "id": "esvZsJrSROKSXLl5fjFXrw",
        "run": 0
      },
      {
        "id": "YrKCBVeeTjmA-f08VKjvZw",
        "run": 0
      },
      {
        "id": "C931P3KRQqeN2_B7arLQCg",
        "run": 0
      },
      {
        "id": "JYHSpoEAQiWMnFnm-qoPHg",
        "run": 0
      },
      {
        "id": "a1QRkn3PQjSPebIAF2U2vg",
        "run": 0
      },
      {
        "id": "dHjGyJTCRHih50ftLWY7Qw",
        "run": 0
      },
      {
        "id": "SMCjFoF2T6yNED7pmuZ_pA",
        "run": 0
      },
      {
        "id": "dng0RgKRRcyAgBVmZUVtgw",
        "run": 0
      },
      {
        "id": "Votb07_6S1KOF-TMWTMBfQ",
        "run": 0
      },
      {
        "id": "cC4Qoh8sRnOiWy9Zhm7L3w",
        "run": 0
      },
      {
        "id": "di1jiiS1Qm2MrmrFt1LH5w",
        "run": 0
      },
      {
        "id": "SMKGoEkDT0iGks6htzaZwg",
        "run": 0
      },
      {
        "id": "dAvI4bYgQ8KF7gMevI6RnQ",
        "run": 0
      },
      {
        "id": "D0RFeSS6Rp-K04dGY0OqIg",
        "run": 0
      },
      {
        "id": "BASIFb9VT4G2TkYhBPdqYA",
        "run": 0
      },
      {
        "id": "Nq_gjyn3QJ-wCyf3P-XtXw",
        "run": 0
      },
      {
        "id": "YjDupDKfSU-4ODO1rM6XPw",
        "run": 0
      }
    ]
  },
  "state": "working"
}