{
  "machine": {
    "id": "i-0b8a0b98d58353a47",
    "name": "i-0b8a0b98d58353a47",
    "type": "c4.4xlarge",
    "imageId": "ami-051503b3e37cde2f0",
    "cloud": "ec2",
    "zone": "us-east-1b",
    "region": "us-east-1",
    "spawned": "2019-05-14T16:17:30Z"
  },
  "worker": {
    "id": "i-0b8a0b98d58353a47",
    "provisioner": "aws-provisioner-v1",
    "type": "gecko-3-b-linux",
    "group": "us-east-1",
    "implementation": "docker-worker",
    "expires": "0001-01-01T00:00:00Z",
    "firstClaim": "2019-05-14T16:18:27.571Z",
    "tasks": [
      {
        "id": "G-1XyUq9RuWw4stHulqkNw",
        "run": 0
      },
      {
        "id": "ZRU3CisxSlOqwdpGP0wSEA",
        "run": 0
      },
      {
        "id": "O8zNq7kBS46vekQZgEiHHw",
        "run": 0
      },
      {
        "id": "MKY-UTLeRWGTtf7DNXKZ0g",
        "run": 0
      },
      {
        "id": "dFmY8YrlRC6XA8NTJ9t7ng",
        "run": 0
      }
    ]
  },
  "state": "working"
}