{
  "machine": {
    "id": "i-0705b627c0aaa54dc",
    "name": "i-0705b627c0aaa54dc",
    "type": "c4.2xlarge",
    "imageId": "ami-0f5141f400b9e2592",
    "cloud": "ec2",
    "zone": "eu-central-1b",
    "region": "eu-central-1",
    "spawned": "2019-05-13T15:07:26Z"
  },
  "worker": {
    "id": "i-0705b627c0aaa54dc",
    "provisioner": "aws-provisioner-v1",
    "type": "gecko-t-win7-32",
    "group": "eu-central-1",
    "implementation": "generic-worker",
    "expires": "0001-01-01T00:00:00Z",
    "firstClaim": "2019-05-13T15:15:43.756Z",
    "tasks": [
      {
        "id": "D5ZPYnKIRQOyr0YJ0xJxvQ",
        "run": 0
      }
    ]
  },
  "state": "working"
}