{
  "machine": {
    "id": "i-0d2f01000fd763936",
    "name": "i-0d2f01000fd763936",
    "type": "c4.2xlarge",
    "imageId": "ami-0cef403fc7cf0fbdf",
    "cloud": "ec2",
    "zone": "us-west-2b",
    "region": "us-west-2",
    "spawned": "2019-05-14T10:56:06Z"
  },
  "worker": {
    "id": "i-0d2f01000fd763936",
    "provisioner": "aws-provisioner-v1",
    "type": "gecko-t-win7-32",
    "group": "us-west-2",
    "implementation": "generic-worker",
    "expires": "0001-01-01T00:00:00Z",
    "firstClaim": "2019-05-14T11:03:26.975Z",
    "tasks": [
      {
        "id": "NCgUixkETP2yIhAFb1byyQ",
        "run": 0
      },
      {
        "id": "ZBGBIxfeQiWNnG4xvoafJQ",
        "run": 0
      },
      {
        "id": "f8wVSLMvRl-i9DOxcxUFdA",
        "run": 0
      },
      {
        "id": "T8fvKUscRReXjosHEqd3yw",
        "run": 0
      },
      {
        "id": "cTA79JOKRbSPYy3MDgHs3Q",
        "run": 0
      },
      {
        "id": "XjHB2G1dTEmfDmbC1QUFAQ",
        "run": 0
      },
      {
        "id": "MTgeJBhLS_eDOw5hTuUGlw",
        "run": 0
      },
      {
        "id": "ZmH1qsxZRturcVf4HPPcyQ",
        "run": 0
      },
      {
        "id": "GesP6UnYTUS0sadT6y0qRw",
        "run": 0
      }
    ]
  },
  "state": "working"
}