{
  "machine": {
    "id": "i-0f8e76b7dedb161c2",
    "name": "i-0f8e76b7dedb161c2",
    "type": "c4.2xlarge",
    "imageId": "ami-040d7ec8248187cdc",
    "cloud": "ec2",
    "zone": "us-east-1c",
    "region": "us-east-1",
    "spawned": "2019-05-13T09:42:48Z"
  },
  "worker": {
    "id": "i-0f8e76b7dedb161c2",
    "provisioner": "aws-provisioner-v1",
    "type": "gecko-t-win7-32",
    "group": "us-east-1",
    "implementation": "generic-worker",
    "expires": "0001-01-01T00:00:00Z",
    "firstClaim": "2019-05-13T09:49:46.42Z",
    "tasks": [
      {
        "id": "UyUY1Iu6Stet9QRYwtEIKA",
        "run": 0
      },
      {
        "id": "eRQCL0UgRW6AB_tTL4tWLQ",
        "run": 0
      },
      {
        "id": "UXk1bbmVQUea3JW01EhhJA",
        "run": 0
      },
      {
        "id": "D1bzyOgiSMCzfDOwxPLBrQ",
        "run": 0
      }
    ]
  },
  "state": "working"
}