{
  "machine": {
    "id": "i-09065d69b04f47c22",
    "name": "i-09065d69b04f47c22",
    "type": "m3.xlarge",
    "imageId": "ami-051503b3e37cde2f0",
    "cloud": "ec2",
    "zone": "us-east-1e",
    "region": "us-east-1",
    "spawned": "2019-05-13T09:29:02Z"
  },
  "worker": {
    "id": "i-09065d69b04f47c22",
    "provisioner": "aws-provisioner-v1",
    "type": "gecko-3-t-linux-xlarge",
    "group": "us-east-1",
    "implementation": "docker-worker",
    "expires": "0001-01-01T00:00:00Z",
    "firstClaim": "2019-05-13T09:29:50.522Z",
    "tasks": [
      {
        "id": "A0bXAV-dRaaKzupgfP2ELQ",
        "run": 0
      },
      {
        "id": "A7MCBFlYSjqpRsmeo-X6Rw",
        "run": 0
      },
      {
        "id": "aGUM9jvTRVOci4ReaIg5EQ",
        "run": 0
      },
      {
        "id": "Wnrcpl8dRc2_1luPSjHv-w",
        "run": 0
      }
    ]
  },
  "state": "working"
}