{
  "machine": {
    "id": "i-026c6c88b89d8d3c1",
    "name": "i-026c6c88b89d8d3c1",
    "type": "c4.4xlarge",
    "imageId": "ami-0882bf5a9885999e5",
    "cloud": "ec2",
    "zone": "us-west-1c",
    "region": "us-west-1",
    "spawned": "2019-05-02T16:37:54Z"
  },
  "worker": {
    "id": "i-026c6c88b89d8d3c1",
    "provisioner": "aws-provisioner-v1",
    "type": "gecko-3-b-win2012",
    "group": "us-west-1",
    "implementation": "generic-worker",
    "expires": "0001-01-01T00:00:00Z",
    "firstClaim": "2019-05-02T16:44:31.848Z",
    "tasks": [
      {
        "id": "A6MELNeETReuBS7RGvUevw",
        "run": 0
      },
      {
        "id": "Z-_5ZuiwQKCu6-YV4yzu8A",
        "run": 0
      },
      {
        "id": "TFA5ch2BT16Izw8uzadI1g",
        "run": 0
      },
      {
        "id": "WpOfIit3S2-nWR0EmPhwxQ",
        "run": 0
      },
      {
        "id": "TuMNUjcgSk-O4VoakrhsXg",
        "run": 0
      },
      {
        "id": "JyW4JB0oSfCoclN9cylCsQ",
        "run": 0
      },
      {
        "id": "eTRBw_aJT86f-I8Q8wgy8A",
        "run": 0
      },
      {
        "id": "PVa_wvOORTC7H4ElpIYGhw",
        "run": 0
      },
      {
        "id": "Seo-L4e0RX6sRAVruKEfgA",
        "run": 0
      },
      {
        "id": "ECguWpQ7Qyq6n5--1iQfDQ",
        "run": 0
      },
      {
        "id": "UB0JKK2fQw-YQxb0LBXj1A",
        "run": 0
      },
      {
        "id": "HBlVyKILRNGAzPMBAE9UCg",
        "run": 0
      }
    ]
  },
  "state": "working"
}