{
  "machine": {
    "id": "i-0bbe60d13b1ca3139",
    "name": "i-0bbe60d13b1ca3139",
    "type": "c4.4xlarge",
    "imageId": "ami-0840062a021732411",
    "cloud": "ec2",
    "zone": "us-west-2b",
    "region": "us-west-2",
    "spawned": "2019-05-14T16:29:46Z"
  },
  "worker": {
    "id": "i-0bbe60d13b1ca3139",
    "provisioner": "aws-provisioner-v1",
    "type": "gecko-3-b-win2012",
    "group": "us-west-2",
    "implementation": "generic-worker",
    "expires": "0001-01-01T00:00:00Z",
    "firstClaim": "2019-05-14T16:35:44.643Z",
    "tasks": [
      {
        "id": "T4r6WfLUQ0mxsZBahI_htw",
        "run": 0
      },
      {
        "id": "GqLpFZZ8SkCByBy-4_HPcQ",
        "run": 0
      },
      {
        "id": "Wj9DwMAMTNq3yKdGAhxp1g",
        "run": 0
      },
      {
        "id": "czo2oz1NTEqSe5cB-QA-RA",
        "run": 0
      },
      {
        "id": "fE6IGNdlSwqk4WlyICl3gA",
        "run": 0
      },
      {
        "id": "EFdQa5vsQLeh9iHHZqsOxA",
        "run": 0
      },
      {
        "id": "ejPJER3DR52QddE6tkgaUQ",
        "run": 0
      }
    ]
  },
  "state": "working"
}