{
  "machine": {
    "id": "i-0115b86f0a52a41fa",
    "name": "i-0115b86f0a52a41fa",
    "type": "g3.4xlarge",
    "imageId": "ami-0ef02ad679fd6fb2f",
    "cloud": "ec2",
    "zone": "us-west-1b",
    "region": "us-west-1",
    "spawned": "2019-05-13T18:11:43Z"
  },
  "worker": {
    "id": "i-0115b86f0a52a41fa",
    "provisioner": "aws-provisioner-v1",
    "type": "gecko-t-win10-64-gpu",
    "group": "us-west-1",
    "implementation": "generic-worker",
    "expires": "0001-01-01T00:00:00Z",
    "firstClaim": "2019-05-13T18:22:13.863Z",
    "tasks": [
      {
        "id": "OdbIAe3KSXeBmfpsHRz_ng",
        "run": 0
      },
      {
        "id": "Rcdx5Tq9QHu3FVmf3AoFfg",
        "run": 0
      },
      {
        "id": "EeAaCQn9SjyG1qCRsE2Ynw",
        "run": 0
      }
    ]
  },
  "state": "working"
}