{
  "machine": {
    "id": "i-0ed601e9a44dac28f",
    "name": "i-0ed601e9a44dac28f",
    "type": "g3.4xlarge",
    "imageId": "ami-0ef02ad679fd6fb2f",
    "cloud": "ec2",
    "zone": "us-west-1b",
    "region": "us-west-1",
    "spawned": "2019-05-14T16:29:36Z"
  },
  "worker": {
    "id": "i-0ed601e9a44dac28f",
    "provisioner": "aws-provisioner-v1",
    "type": "gecko-t-win10-64-gpu",
    "group": "us-west-1",
    "implementation": "generic-worker",
    "expires": "0001-01-01T00:00:00Z",
    "firstClaim": "2019-05-14T16:38:27.138Z",
    "tasks": [
      {
        "id": "Z5I-WooRRKS07YePTisKZA",
        "run": 0
      },
      {
        "id": "T0yk7GoSR7OboZQc1h_w0w",
        "run": 0
      },
      {
        "id": "LsmJEpcfR6G0Ha1aGJNihA",
        "run": 0
      },
      {
        "id": "RFnYUoPyToO2uTk2I1uMqA",
        "run": 0
      },
      {
        "id": "DlIUU6agQ02c_wCVAXaI0Q",
        "run": 0
      }
    ]
  },
  "state": "working"
}