{
  "machine": {
    "id": "i-0108146c610cd4f1e",
    "name": "i-0108146c610cd4f1e",
    "type": "m3.large",
    "imageId": "ami-06adcae0cf519fda6",
    "cloud": "ec2",
    "zone": "us-west-1c",
    "region": "us-west-1",
    "spawned": "2019-05-02T10:12:52Z"
  },
  "worker": {
    "id": "i-0108146c610cd4f1e",
    "provisioner": "aws-provisioner-v1",
    "type": "gecko-t-linux-large",
    "group": "us-west-1",
    "implementation": "docker-worker",
    "expires": "0001-01-01T00:00:00Z",
    "firstClaim": "2019-05-02T10:13:39.852Z",
    "tasks": [
      {
        "id": "dSPxUTJZTwewjsm8GZsFvQ",
        "run": 0
      },
      {
        "id": "PCi2q3SGSFyETS8dpgXAqw",
        "run": 0
      },
      {
        "id": "NvOcRBgGTViUMgBqMK17gg",
        "run": 0
      },
      {
        "id": "U2EJdmkBSrqxYTGys6j-Jw",
        "run": 0
      },
      {
        "id": "XboSy9lMTMiJhHBvjZK8BQ",
        "run": 0
      },
      {
        "id": "IjbvPOmzSdGMwm5_fPU1jQ",
        "run": 0
      },
      {
        "id": "cbeRLnlAQBelPdLWDOH8SA",
        "run": 0
      },
      {
        "id": "J0tC5SrUQkKpg7dTWPwe_w",
        "run": 0
      },
      {
        "id": "Jhg-JgSLSl6vXgFouEhnWw",
        "run": 0
      },
      {
        "id": "BSTzYL07SBKqJ3UO54o8cA",
        "run": 0
      },
      {
        "id": "fL3KIUMjQdKdb8rCUVmkSw",
        "run": 0
      },
      {
        "id": "S3w_aogQQm68X6CIAWe1Nw",
        "run": 0
      },
      {
        "id": "TrIhBLLaQaKt_ikJOz24mA",
        "run": 0
      }
    ]
  },
  "state": "working"
}