{
  "machine": {
    "id": "i-01cf230e467aec0be",
    "name": "i-01cf230e467aec0be",
    "type": "m3.large",
    "imageId": "ami-06adcae0cf519fda6",
    "cloud": "ec2",
    "zone": "us-west-1c",
    "region": "us-west-1",
    "spawned": "2019-05-14T10:36:09Z"
  },
  "worker": {
    "id": "i-01cf230e467aec0be",
    "provisioner": "aws-provisioner-v1",
    "type": "gecko-t-linux-large",
    "group": "us-west-1",
    "implementation": "docker-worker",
    "expires": "0001-01-01T00:00:00Z",
    "firstClaim": "2019-05-14T10:37:07.06Z",
    "tasks": [
      {
        "id": "fNXgsmTmT8asajjU513M8A",
        "run": 0
      },
      {
        "id": "ebryXBSBQeu546US3R0J_Q",
        "run": 0
      },
      {
        "id": "JEdTBNdoR9KFdk2nrdlCFA",
        "run": 0
      },
      {
        "id": "RjdRGHEzQ2u0UWxTojVr1A",
        "run": 0
      },
      {
        "id": "ExZT_weCQxC4iDJfmpmvAA",
        "run": 0
      },
      {
        "id": "bEmwFztMRviwyzZoh1nHEg",
        "run": 0
      },
      {
        "id": "DDBmzX-IRq20afO4J3qV4g",
        "run": 0
      },
      {
        "id": "VlmA-yH6RF62KySLYYlA_g",
        "run": 0
      }
    ]
  },
  "state": "working"
}