{
  "machine": {
    "id": "i-023cdbc1178e9320a",
    "name": "i-023cdbc1178e9320a",
    "type": "m3.large",
    "imageId": "ami-0dedc5db10ec003af",
    "cloud": "ec2",
    "zone": "us-east-1d",
    "region": "us-east-1",
    "spawned": "2019-05-03T05:07:36Z"
  },
  "worker": {
    "id": "i-023cdbc1178e9320a",
    "provisioner": "aws-provisioner-v1",
    "type": "gecko-t-linux-large",
    "group": "us-east-1",
    "implementation": "docker-worker",
    "expires": "0001-01-01T00:00:00Z",
    "firstClaim": "2019-05-03T05:08:29.345Z",
    "tasks": [
      {
        "id": "YANEGSUZTbGkWrBDtG639g",
        "run": 0
      },
      {
        "id": "Yr8wxRC3RLKpYGiFMbO1Lg",
        "run": 0
      },
      {
        "id": "MqSCnmJ2TJajeLojoWQAdw",
        "run": 0
      },
      {
        "id": "Tdh1v_GgTuy1bEfH95TYNA",
        "run": 0
      },
      {
        "id": "GTpT9pj6RMegJc8W31A9RQ",
        "run": 0
      },
      {
        "id": "PfBsg6mmQdaHgRqNPGwevw",
        "run": 0
      },
      {
        "id": "XeeAtLXaTjybQ7wI8GG2rw",
        "run": 0
      },
      {
        "id": "dachfmSCSUK4qutaDtJrag",
        "run": 0
      },
      {
        "id": "MZMJDv1vSrGSfRTqB3AL6A",
        "run": 0
      },
      {
        "id": "KDRBoTCTR2y9fwwquBTDKA",
        "run": 0
      },
      {
        "id": "GCZp7FqqRWaZXq8ymXG-vw",
        "run": 0
      },
      {
        "id": "LOpCLF3hQ7uZ9_ojrZ3tzg",
        "run": 0
      }
    ]
  },
  "state": "working"
}