{
  "machine": {
    "id": "i-0330035f907d1c745",
    "name": "i-0330035f907d1c745",
    "type": "m3.large",
    "imageId": "ami-06adcae0cf519fda6",
    "cloud": "ec2",
    "zone": "us-west-1b",
    "region": "us-west-1",
    "spawned": "2019-05-02T08:56:28Z"
  },
  "worker": {
    "id": "i-0330035f907d1c745",
    "provisioner": "aws-provisioner-v1",
    "type": "gecko-t-linux-large",
    "group": "us-west-1",
    "implementation": "docker-worker",
    "expires": "0001-01-01T00:00:00Z",
    "firstClaim": "2019-05-02T08:57:14.81Z",
    "tasks": [
      {
        "id": "FhCiF7-uS3qMKFwpnwRpww",
        "run": 0
      },
      {
        "id": "RLVQiT4fSAaj3NTz_YiaXw",
        "run": 0
      },
      {
        "id": "IfHEvar-SFWezsCYcI5-6A",
        "run": 0
      },
      {
        "id": "bsKIzCkKQoiZ5Jvq__02Ng",
        "run": 0
      },
      {
        "id": "Zp11LXhsTxOByFG-h1DCww",
        "run": 0
      },
      {
        "id": "EE1k-AJHTrGauJB-K909Bg",
        "run": 0
      },
      {
        "id": "eI9g9bxtT5CcFTY4OstumQ",
        "run": 0
      },
      {
        "id": "RZsgYCgYSUuwK8n8H5TPwQ",
        "run": 0
      },
      {
        "id": "Qivvi4d7SJqt6R9f8QnU7w",
        "run": 0
      },
      {
        "id": "MC8V0YF4S52Uk9wcBgMs2g",
        "run": 0
      },
      {
        "id": "SYGd6vBbRv-h2qveUwUPQg",
        "run": 0
      },
      {
        "id": "d8sflrqVRJCY5Z5SDJRHxA",
        "run": 0
      },
      {
        "id": "V8WsDnfOS76zDCrsifSBbg",
        "run": 0
      },
      {
        "id": "AeMG_ZPbSR20zEYcl84Qtg",
        "run": 0
      },
      {
        "id": "FME-rPpDSamocZzRIjsfeQ",
        "run": 0
      },
      {
        "id": "DIxZKPskR5SpSbLgUQjLyg",
        "run": 0
      }
    ]
  },
  "state": "working"
}