{
  "machine": {
    "id": "i-039e26226edbdb10c",
    "name": "i-039e26226edbdb10c",
    "type": "m3.large",
    "imageId": "ami-06adcae0cf519fda6",
    "cloud": "ec2",
    "zone": "us-west-1b",
    "region": "us-west-1",
    "spawned": "2019-05-07T10:36:32Z"
  },
  "worker": {
    "id": "i-039e26226edbdb10c",
    "provisioner": "aws-provisioner-v1",
    "type": "gecko-t-linux-large",
    "group": "us-west-1",
    "implementation": "docker-worker",
    "expires": "0001-01-01T00:00:00Z",
    "firstClaim": "2019-05-07T10:37:30.21Z",
    "tasks": [
      {
        "id": "VDcdKnDqS6CpTL5EFm_xVQ",
        "run": 0
      },
      {
        "id": "PLXhoUUpRQ60Xwp9ZeBkYg",
        "run": 0
      },
      {
        "id": "MD4noYpkSEuBOVsLjIhVyw",
        "run": 0
      },
      {
        "id": "HcZtmnKyRWKdx4Cu9v68aA",
        "run": 0
      },
      {
        "id": "R3yxohQaQbGcmkhO_IyyrQ",
        "run": 0
      },
      {
        "id": "Wb9aQQgwRoW-wezVUwL0jg",
        "run": 0
      },
      {
        "id": "Nlp7ZDPZRMevcfhOw5Je7A",
        "run": 0
      },
      {
        "id": "GZNLpF6-RnGbALe8mauLfg",
        "run": 0
      }
    ]
  },
  "state": "working"
}