{
  "machine": {
    "id": "i-07d760734f4118b37",
    "name": "i-07d760734f4118b37",
    "type": "m3.large",
    "imageId": "ami-06adcae0cf519fda6",
    "cloud": "ec2",
    "zone": "us-west-1c",
    "region": "us-west-1",
    "spawned": "2019-05-13T17:59:23Z"
  },
  "worker": {
    "id": "i-07d760734f4118b37",
    "provisioner": "aws-provisioner-v1",
    "type": "gecko-t-linux-large",
    "group": "us-west-1",
    "implementation": "docker-worker",
    "expires": "0001-01-01T00:00:00Z",
    "firstClaim": "2019-05-13T18:00:04.226Z",
    "tasks": [
      {
        "id": "RRrUv2JxQhyUqCtAdAzUnQ",
        "run": 0
      },
      {
        "id": "WRKguWXMS92q_NouAa-kKA",
        "run": 0
      },
      {
        "id": "a4fW7f07STOen2liVCyM-w",
        "run": 0
      },
      {
        "id": "ExtZ9HqwQZCcsA9DJvQ1Gw",
        "run": 0
      },
      {
        "id": "RLgm81nsQEWvozGInizGjw",
        "run": 0
      },
      {
        "id": "MnVVoXwARyO3pS9xNzMUNQ",
        "run": 0
      },
      {
        "id": "RvRwOE-fSYC_wbBu2Y4h-Q",
        "run": 0
      },
      {
        "id": "B1DeF10oR7OIKh4M7fU_-Q",
        "run": 0
      }
    ]
  },
  "state": "working"
}