{
  "machine": {
    "id": "i-08a0201e6345b8a69",
    "name": "i-08a0201e6345b8a69",
    "type": "m3.large",
    "imageId": "ami-06adcae0cf519fda6",
    "cloud": "ec2",
    "zone": "us-west-1b",
    "region": "us-west-1",
    "spawned": "2019-05-03T05:23:13Z"
  },
  "worker": {
    "id": "i-08a0201e6345b8a69",
    "provisioner": "aws-provisioner-v1",
    "type": "gecko-t-linux-large",
    "group": "us-west-1",
    "implementation": "docker-worker",
    "expires": "0001-01-01T00:00:00Z",
    "firstClaim": "2019-05-03T05:23:55.235Z",
    "tasks": [
      {
        "id": "RvRWV_ODROSEUlZJhf89Qg",
        "run": 0
      },
      {
        "id": "Y72cEWn4TV-xkWGfFKEtkQ",
        "run": 0
      }
    ]
  },
  "state": "working"
}