{
  "machine": {
    "id": "i-0a0d10a807b8cab59",
    "name": "i-0a0d10a807b8cab59",
    "type": "m3.large",
    "imageId": "ami-06adcae0cf519fda6",
    "cloud": "ec2",
    "zone": "us-west-1b",
    "region": "us-west-1",
    "spawned": "2019-05-07T09:17:59Z"
  },
  "worker": {
    "id": "i-0a0d10a807b8cab59",
    "provisioner": "aws-provisioner-v1",
    "type": "gecko-t-linux-large",
    "group": "us-west-1",
    "implementation": "docker-worker",
    "expires": "0001-01-01T00:00:00Z",
    "firstClaim": "2019-05-07T09:18:41.953Z",
    "tasks": [
      {
        "id": "LNBSc8MAQBSjDraqd37NrA",
        "run": 0
      },
      {
        "id": "NIa5r4ouS-qasr5k3zJOrw",
        "run": 0
      },
      {
        "id": "c9wOEWsXSxKydDlwk5Ur5A",
        "run": 0
      },
      {
        "id": "Ql4EvwmlQLOBE1X9-P6Rvg",
        "run": 0
      },
      {
        "id": "IFPlkx_cRl2CrYV5dq4bfg",
        "run": 0
      },
      {
        "id": "HGK-zLwUT1-K5x3lZlX9nA",
        "run": 0
      }
    ]
  },
  "state": "working"
}