{
  "machine": {
    "id": "i-0dee87b9bac655b90",
    "name": "i-0dee87b9bac655b90",
    "type": "m3.large",
    "imageId": "ami-06adcae0cf519fda6",
    "cloud": "ec2",
    "zone": "us-west-1c",
    "region": "us-west-1",
    "spawned": "2019-05-13T22:40:51Z"
  },
  "worker": {
    "id": "i-0dee87b9bac655b90",
    "provisioner": "aws-provisioner-v1",
    "type": "gecko-t-linux-large",
    "group": "us-west-1",
    "implementation": "docker-worker",
    "expires": "0001-01-01T00:00:00Z",
    "firstClaim": "2019-05-13T22:41:38.276Z",
    "tasks": [
      {
        "id": "HbtYT3UiSSGZIrOzXlPdDw",
        "run": 0
      },
      {
        "id": "H8fN-anASk2ApDBOJkuwMw",
        "run": 0
      },
      {
        "id": "CFctJxQwTfGihEzESYtYSA",
        "run": 0
      },
      {
        "id": "cgHkKwWTS6iHRW_6jEfFzw",
        "run": 0
      },
      {
        "id": "brE0hDwpS4mWjYtHvrEiXg",
        "run": 0
      },
      {
        "id": "DtJHEXZtR4eZfY7yF-q2Nw",
        "run": 0
      },
      {
        "id": "Ln9EsP7jSJ2RUnVYg1i2ag",
        "run": 0
      }
    ]
  },
  "state": "working"
}