{
  "machine": {
    "id": "i-0fdec0fb294792a14",
    "name": "i-0fdec0fb294792a14",
    "type": "m3.large",
    "imageId": "ami-07a6e593eb16d27fa",
    "cloud": "ec2",
    "zone": "us-west-2a",
    "region": "us-west-2",
    "spawned": "2019-05-13T20:46:36Z"
  },
  "worker": {
    "id": "i-0fdec0fb294792a14",
    "provisioner": "aws-provisioner-v1",
    "type": "gecko-t-linux-large",
    "group": "us-west-2",
    "implementation": "docker-worker",
    "expires": "0001-01-01T00:00:00Z",
    "firstClaim": "2019-05-13T20:47:21.18Z",
    "tasks": [
      {
        "id": "Lzi3riDmTgm_5RqEocYQCw",
        "run": 0
      },
      {
        "id": "bQi669ELSeKeaH9A_l7UmQ",
        "run": 0
      },
      {
        "id": "bY5BIq6mTVyN8vr5VZfqfw",
        "run": 0
      },
      {
        "id": "afizahVjQWqItJf9__nMOg",
        "run": 0
      }
    ]
  },
  "state": "working"
}