{
  "machine": {
    "id": "i-0291c0e122b8ea21c",
    "name": "i-0291c0e122b8ea21c",
    "type": "c3.xlarge",
    "imageId": "ami-06adcae0cf519fda6",
    "cloud": "ec2",
    "zone": "us-west-1c",
    "region": "us-west-1",
    "spawned": "2019-05-14T08:10:20Z"
  },
  "worker": {
    "id": "i-0291c0e122b8ea21c",
    "provisioner": "aws-provisioner-v1",
    "type": "gecko-t-linux-xlarge",
    "group": "us-west-1",
    "implementation": "docker-worker",
    "expires": "0001-01-01T00:00:00Z",
    "firstClaim": "2019-05-14T08:11:14.428Z",
    "tasks": [
      {
        "id": "JSTmceMeQiOk74L1o8yPCA",
        "run": 0
      }
    ]
  },
  "state": "working"
}