{
  "machine": {
    "id": "i-04ff396f904b92f17",
    "name": "i-04ff396f904b92f17",
    "type": "m3.xlarge",
    "imageId": "ami-0dedc5db10ec003af",
    "cloud": "ec2",
    "zone": "us-east-1c",
    "region": "us-east-1",
    "spawned": "2019-05-01T21:34:17Z"
  },
  "worker": {
    "id": "i-04ff396f904b92f17",
    "provisioner": "aws-provisioner-v1",
    "type": "gecko-t-linux-xlarge",
    "group": "us-east-1",
    "implementation": "docker-worker",
    "expires": "0001-01-01T00:00:00Z",
    "firstClaim": "2019-05-01T21:35:18.415Z",
    "tasks": [
      {
        "id": "bquryTJ0SDybt3z5EbLLaA",
        "run": 0
      },
      {
        "id": "ZAeaKGFFTiuKDrs0lR_HoQ",
        "run": 0
      },
      {
        "id": "Y0Ga2YYzQ2-HL-2FTTSUqw",
        "run": 0
      },
      {
        "id": "eo1GD_93SU-5tOwSu_jg7A",
        "run": 0
      },
      {
        "id": "MzI2X1lFQuSbbufMKb_fxA",
        "run": 0
      },
      {
        "id": "Vfm2iz0nSze_-yLufglZFA",
        "run": 0
      },
      {
        "id": "criE79HYTqWcSy8D2cI8bw",
        "run": 0
      },
      {
        "id": "JIWRhwkBSHucmNGpjUQ9Wg",
        "run": 0
      },
      {
        "id": "E6n4wclbRRm6ey2Xv11Pcw",
        "run": 0
      },
      {
        "id": "UmM_vlxgSBi2SqdvBfpRRQ",
        "run": 0
      },
      {
        "id": "NMsLEOXVSpqxk5_MISjv8g",
        "run": 0
      },
      {
        "id": "csN7ID7vQmawDpEMpSy92Q",
        "run": 0
      },
      {
        "id": "OFCjVtx6RlKRyZBpI7AGqg",
        "run": 0
      },
      {
        "id": "fG97-LlwS2-dKYhTSkZMCg",
        "run": 0
      },
      {
        "id": "QxP25kgXSVKY7gV-JlALlg",
        "run": 0
      },
      {
        "id": "TT_AkHAhQYqtwl18M3exqg",
        "run": 0
      },
      {
        "id": "CPvBrji3RZihA23FOr6nwA",
        "run": 0
      },
      {
        "id": "CqogaqWwQu2mKg17dSh8Zw",
        "run": 0
      }
    ]
  },
  "state": "working"
}