{
  "machine": {
    "id": "i-04f8acc9dcdee7942",
    "name": "i-04f8acc9dcdee7942",
    "type": "m3.xlarge",
    "imageId": "ami-07a6e593eb16d27fa",
    "cloud": "ec2",
    "zone": "us-west-2b",
    "region": "us-west-2",
    "spawned": "2019-05-03T00:18:21Z"
  },
  "worker": {
    "id": "i-04f8acc9dcdee7942",
    "provisioner": "aws-provisioner-v1",
    "type": "gecko-t-linux-xlarge",
    "group": "us-west-2",
    "implementation": "docker-worker",
    "expires": "0001-01-01T00:00:00Z",
    "firstClaim": "2019-05-03T00:19:09.462Z",
    "tasks": [
      {
        "id": "LC3PC729TsSEjP3k6FDCtQ",
        "run": 0
      },
      {
        "id": "KNN7ddSlRGunj6iXB_kDkQ",
        "run": 0
      },
      {
        "id": "FBPT0W-8QUey55vfgxLVqg",
        "run": 0
      },
      {
        "id": "KFh7lkaPRcegzXbo5sQ6kw",
        "run": 0
      },
      {
        "id": "TdT4kl-DRDqi6oKBysLZtw",
        "run": 0
      },
      {
        "id": "TtPSqZf9T2CZlsF3LP229w",
        "run": 0
      },
      {
        "id": "ZNK1cBESTeybcC6K9yB8HA",
        "run": 0
      },
      {
        "id": "N7OjZAD8T32l0v2e_3yMEg",
        "run": 0
      }
    ]
  },
  "state": "working"
}