{
  "machine": {
    "id": "i-084db9173ddf9e9e6",
    "name": "i-084db9173ddf9e9e6",
    "type": "m3.xlarge",
    "imageId": "ami-0dedc5db10ec003af",
    "cloud": "ec2",
    "zone": "us-east-1a",
    "region": "us-east-1",
    "spawned": "2019-05-14T11:44:22Z"
  },
  "worker": {
    "id": "i-084db9173ddf9e9e6",
    "provisioner": "aws-provisioner-v1",
    "type": "gecko-t-linux-xlarge",
    "group": "us-east-1",
    "implementation": "docker-worker",
    "expires": "0001-01-01T00:00:00Z",
    "firstClaim": "2019-05-14T11:45:14.642Z",
    "tasks": [
      {
        "id": "fUjEfgsNT0uuuDmVMd712Q",
        "run": 0
      },
      {
        "id": "AnUh1tcKSSqY_IofkrZ-Gg",
        "run": 0
      },
      {
        "id": "MmUA_M4WSgqNdC6hwZY6Kg",
        "run": 0
      },
      {
        "id": "dknBvWlLS2CIoJENpE2y-w",
        "run": 0
      },
      {
        "id": "G90rdAeNTLGaPtGFWWHQOg",
        "run": 1
      },
      {
        "id": "W2Y0YTmITuGK-FvAf_8HXg",
        "run": 0
      },
      {
        "id": "OefBskdjQyK9whNA7J2nKQ",
        "run": 0
      },
      {
        "id": "QVlHYB66SiuiqOiTKe58Ow",
        "run": 0
      }
    ]
  },
  "state": "working"
}