{
  "machine": {
    "id": "i-08e604a3414eb5fce",
    "name": "i-08e604a3414eb5fce",
    "type": "m3.xlarge",
    "imageId": "ami-0dedc5db10ec003af",
    "cloud": "ec2",
    "zone": "us-east-1e",
    "region": "us-east-1",
    "spawned": "2019-05-13T09:12:46Z"
  },
  "worker": {
    "id": "i-08e604a3414eb5fce",
    "provisioner": "aws-provisioner-v1",
    "type": "gecko-t-linux-xlarge",
    "group": "us-east-1",
    "implementation": "docker-worker",
    "expires": "0001-01-01T00:00:00Z",
    "firstClaim": "2019-05-13T09:13:26.431Z",
    "tasks": [
      {
        "id": "UpQQsv81Qdeys2w_kwU1-Q",
        "run": 0
      },
      {
        "id": "Z52f990gRFSQ5Fbc-4uryw",
        "run": 0
      },
      {
        "id": "BJiYKpeGTUSKW0yJoOnB-w",
        "run": 0
      }
    ]
  },
  "state": "working"
}