{
  "machine": {
    "id": "i-0f38afb537960d585",
    "name": "i-0f38afb537960d585",
    "type": "m3.xlarge",
    "imageId": "ami-06adcae0cf519fda6",
    "cloud": "ec2",
    "zone": "us-west-1c",
    "region": "us-west-1",
    "spawned": "2019-05-07T20:08:09Z"
  },
  "worker": {
    "id": "i-0f38afb537960d585",
    "provisioner": "aws-provisioner-v1",
    "type": "gecko-t-linux-xlarge",
    "group": "us-west-1",
    "implementation": "docker-worker",
    "expires": "0001-01-01T00:00:00Z",
    "firstClaim": "2019-05-07T20:08:58.594Z",
    "tasks": [
      {
        "id": "caIDUWI_S9W4aUan2dpWCw",
        "run": 0
      },
      {
        "id": "TFrI5z8ZR_yKBRRdAbWzDQ",
        "run": 0
      },
      {
        "id": "UCrnJEFDQ4ulVNZ0JO_Mag",
        "run": 0
      }
    ]
  },
  "state": "working"
}